game_sdk/__init__.py
game_sdk/ai_client.py
game_sdk/client.py
game_sdk/dynamic_mcts_agent.py
game_sdk/event_listener.py
game_sdk/event_publisher.py
game_sdk/events.py
game_sdk/integration.py
game_sdk/mcts.py
game_sdk/ml_client.py
game_sdk/rabbitmq.py
game_sdk/registration.py
game_sdk/selfplay_runner.py
game_sdk/utils.py
game_ai_client-1.2.3.dist-info/METADATA
game_ai_client-1.2.3.dist-info/WHEEL
game_ai_client-1.2.3.dist-info/top_level.txt
game_ai_client-1.2.3.dist-info/RECORD
