Metadata-Version: 2.4
Name: game-ai-client
Version: 1.2.3
Summary: Client + MCTS helpers for board game AI integration with self-play support.
Requires-Python: >=3.9
